signalblast/__init__.py
signalblast/admin.py
signalblast/broadcastbot.py
signalblast/commands_strings.py
signalblast/health_check.py
signalblast/log_rollover.py
signalblast/main.py
signalblast/message_handler.py
signalblast/users.py
signalblast/utils.py
signalblast/commands/__init__.py
signalblast/commands/add_admin.py
signalblast/commands/ban_subscriber.py
signalblast/commands/broadcast.py
signalblast/commands/display_help.py
signalblast/commands/last_msg_user_uuid.py
signalblast/commands/lift_ban_subscriber.py
signalblast/commands/message_from_admin.py
signalblast/commands/message_to_admin.py
signalblast/commands/remove_admin.py
signalblast/commands/set_ping.py
signalblast/commands/subscribe.py
signalblast/commands/unset_ping.py
signalblast/commands/unsubscribe.py
signalblast-0.11.0.dist-info/METADATA
signalblast-0.11.0.dist-info/WHEEL
signalblast-0.11.0.dist-info/licenses/LICENSE
signalblast-0.11.0.dist-info/RECORD
