Metadata-Version: 2.4
Name: signalblast
Version: 0.11.0
Summary: Broadcast bot for Signal
Author: Era Dorta
License-File: LICENSE
Keywords: Bot,Broadcast,Signal
Classifier: Programming Language :: Python :: 3
Requires-Python: >=3.10
Requires-Dist: bcrypt>=5.0.0
Requires-Dist: pydantic>=2.12.3
Requires-Dist: signalbot>=0.20.0
